Workbook

Sheet How to use
A1: Carpentry quoting calculator
A3: Yellow cells with blue text are the only cells you type in. Everything else calculates itself.
A5: 1. Rates tab: set your labour rates, margin and supplier prices once. Update board prices when your supplier changes them.
A6: 2. Deck Quote tab: type the deck size, height, board type, steps and balustrade. It gives the price, deposit and warnings.
A7: 3. Job Quote tab: for doors, repairs and small renovations. List hours and materials at your cost; it adds margin and GST.
A8: 4. Copy the final numbers into the ServiceM8 quote (use the matching job template).
A10: Warnings (red) follow NSW rules: written contract over $5,000; HBCF insurance + large job contract over $20,000;
A11: deposit capped at 10%; decks over 1 m high or 25 m2 usually need council/certifier approval.
A13: All starting prices are estimates from October 2026 research (Sydney cost guides). Replace them with your own supplier quotes.
A14: Example values are filled in so you can see how it works. Overwrite them for each job (save a copy per job, or just overwrite).

Sheet Rates
A1: Rates and prices (all ex GST)
A3: General
A4: Labour rate | B4: 90 | C4: $/hour | D4: Sydney typical $63–150/hr inc GST, avg ~$98 (whatsthedamage.com.au, Oct 2026). $90 ex GST = $99 inc.
A5: Materials margin | B5: 0.15 | C5: % | D5: Added to supplier cost: covers pick-up, waste, price risk.
A6: Contingency (old houses / hidden structure) | B6: 0.1 | C6: % | D6: Only applied when you tick it on the quote tab.
A7: GST | B7: 0.1 | C7: % | D7: Australian GST.
A8: Deposit | B8: 0.1 | C8: % | D8: NSW maximum deposit is 10% (NSW Fair Trading). Do not raise.
A9: Minimum charge | B9: 180 | C9: $ | D9: Covers travel + first 2 hours.
A10: Rubbish removal (standard) | B10: 250 | C10: $ | D10: Ute load to tip. Use skip price for big jobs.
A11: Deck labour
A12: Framing labour | B12: 95 | C12: $/m2 | D12: Sydney deck framing labour typical ~$105/m2 inc GST (whatsthedamage.com.au).
A13: Board laying labour | B13: 55 | C13: $/m2 | D13: Estimate; check against your own hours.
A14: Stairs labour | B14: 150 | C14: $/step | D14: Estimate.
A15: Balustrade labour | B15: 180 | C15: $/lin m | D15: Estimate.
A16: Sand & oil (incl. oil) | B16: 30 | C16: $/m2 | D16: Estimate.
A17: Deck materials (supplier cost)
A18: Frame materials: low deck (stirrups/footings, bearers, joists, fixings) | B18: 60 | C18: $/m2 | D18: Estimate for H3/H4 treated pine frame. Get a takeoff price from your timber yard.
A19: Extra frame materials if over 1 m high | B19: 25 | C19: $/m2 | D19: Longer posts, bracing.
A20: Stairs materials | B20: 90 | C20: $/step | D20: Estimate.
A21: Balustrade materials | B21: 150 | C21: $/lin m | D21: Estimate, timber posts/rails/balusters.
A23: Decking boards: supply price (supplier cost)
A24: Board type | B24: $/m2 | D24: Estimates incl. ~10% offcut waste. Update from your supplier.
A25: Treated pine | B25: 45
A26: Merbau | B26: 95
A27: Spotted gum | B27: 115
A28: Blackbutt | B28: 105
A29: Composite | B29: 150
A31: Site difficulty | B31: Labour x
A32: Easy (flat, good access) | B32: 1
A33: Sloped or tight access | B33: 1.15
A34: Difficult (steep, carry-in, demo) | B34: 1.3

Sheet Deck Quote
A1: Deck quote
A3: Inputs
A4: Client / job | B4: Example: Smith, Marrickville
A5: Length (m) | B5: 6
A6: Width (m) | B6: 4
A7: Height off ground (mm) | B7: 600
A8: Board type | B8: Merbau
A9: Number of steps | B9: 3
A10: Balustrade (lin m) | B10: 0
A11: Sand & oil? (Y/N) | B11: Y
A12: Rubbish removal? (Y/N) | B12: Y
A13: Site difficulty | B13: Easy (flat, good access)
A14: Add contingency? (Y/N) | B14: N
A16: Calculation (ex GST) | C16: Labour | D16: Materials
A17: Deck area (m2) | B17: =B5*B6 -> 24
A18: Site difficulty multiplier | B18: =IFERROR(INDEX(Rates!$B$32:$B$34,MATCH(B13,Rates!$A$32:$A$34,0)),1) -> 1
A19: Frame | C19: =B17*Rates!$B$12*B18 -> 2280 | D19: =B17*(Rates!$B$18+IF(B7>1000,Rates!$B$19,0)) -> 1440
A20: Boards | C20: =B17*Rates!$B$13*B18 -> 1320 | D20: =B17*IFERROR(INDEX(Rates!$B$25:$B$29,MATCH(B8,Rates!$A$25:$A$29,0)),0) -> 2280
A21: Stairs | C21: =B9*Rates!$B$14*B18 -> 450 | D21: =B9*Rates!$B$20 -> 270
A22: Balustrade | C22: =B10*Rates!$B$15*B18 -> 0 | D22: =B10*Rates!$B$21 -> 0
A23: Sand & oil | C23: =IF(B11="Y",B17*Rates!$B$16,0) -> 720
A24: Rubbish removal | C24: =IF(B12="Y",Rates!$B$10,0) -> 250
A26: Labour subtotal | B26: =SUM(C19:C24) -> 5020
A27: Materials at cost | B27: =SUM(D19:D24) -> 3990
A28: Materials margin | B28: =B27*Rates!$B$5 -> 598.5
A29: Contingency | B29: =IF(B14="Y",(B26+B27+B28)*Rates!$B$6,0) -> 0
A30: Price ex GST | B30: =ROUND(B26+B27+B28+B29,0) -> 9609
A31: GST | B31: =ROUND(B30*Rates!$B$7,0) -> 961
A32: TOTAL inc GST | B32: =B30+B31 -> 10570
A33: Deposit on acceptance (10% max) | B33: =ROUND(B32*Rates!$B$8,0) -> 1057
A34: Price per m2 inc GST | B34: =IF(B17>0,B32/B17,0) -> 440.41667
A35: Estimated labour hours (for scheduling) | B35: =IF(Rates!$B$4>0,B26/Rates!$B$4,0) -> 55.777778
A37: Checks (NSW)
A38: Written contract needed (over $5,000 inc GST)? | B38: =IF(B32>5000,"YES: small jobs contract before starting","No") -> YES: small jobs contract before starting
A39: Large job contract + HBCF insurance (over $20,000)? | B39: =IF(B32>20000,"YES: get icare HBCF cover BEFORE taking deposit","No") -> No
A40: Council / certifier approval likely (over 1 m high or over 25 m2)? | B40: =IF(OR(B7>1000,B17>25),"YES: check exempt development rules before quoting","No") -> No
A41: Balustrade needed (over 1 m high)? | B41: =IF(AND(B7>1000,B10=0),"YES: add balustrade (lin m)","No") -> No

Sheet Job Quote
A1: General job quote (doors, repairs, small renovations)
A3: Client / job | B3: Example: Nguyen, Newtown: 3 doors + architraves
A4: Add contingency? (Y/N) | B4: N
A6: Item | B6: Type | C6: Qty | D6: Unit cost / rate ($ ex GST) | E6: Line total ex GST
A7: Remove old doors, install 3 prehung doors | B7: Labour hours | C7: 6 | E7: =IF(B7="Labour hours",C7*IF(D7="",Rates!$B$4,D7),IF(B7="Materials at cost",C7*D7*(1+Rates!$B$5),IF(B7="Fixed price item",C7*D7,0))) -> 540
A8: 3 x prehung door sets (supplier) | B8: Materials at cost | C8: 3 | D8: 210 | E8: =IF(B8="Labour hours",C8*IF(D8="",Rates!$B$4,D8),IF(B8="Materials at cost",C8*D8*(1+Rates!$B$5),IF(B8="Fixed price item",C8*D8,0))) -> 724.5
A9: Architraves + fixings | B9: Materials at cost | C9: 1 | D9: 120 | E9: =IF(B9="Labour hours",C9*IF(D9="",Rates!$B$4,D9),IF(B9="Materials at cost",C9*D9*(1+Rates!$B$5),IF(B9="Fixed price item",C9*D9,0))) -> 138
A10: Rubbish removal | B10: Fixed price item | C10: 1 | D10: 250 | E10: =IF(B10="Labour hours",C10*IF(D10="",Rates!$B$4,D10),IF(B10="Materials at cost",C10*D10*(1+Rates!$B$5),IF(B10="Fixed price item",C10*D10,0))) -> 250
E11: =IF(B11="Labour hours",C11*IF(D11="",Rates!$B$4,D11),IF(B11="Materials at cost",C11*D11*(1+Rates!$B$5),IF(B11="Fixed price item",C11*D11,0))) -> 0
E12: =IF(B12="Labour hours",C12*IF(D12="",Rates!$B$4,D12),IF(B12="Materials at cost",C12*D12*(1+Rates!$B$5),IF(B12="Fixed price item",C12*D12,0))) -> 0
E13: =IF(B13="Labour hours",C13*IF(D13="",Rates!$B$4,D13),IF(B13="Materials at cost",C13*D13*(1+Rates!$B$5),IF(B13="Fixed price item",C13*D13,0))) -> 0
E14: =IF(B14="Labour hours",C14*IF(D14="",Rates!$B$4,D14),IF(B14="Materials at cost",C14*D14*(1+Rates!$B$5),IF(B14="Fixed price item",C14*D14,0))) -> 0
E15: =IF(B15="Labour hours",C15*IF(D15="",Rates!$B$4,D15),IF(B15="Materials at cost",C15*D15*(1+Rates!$B$5),IF(B15="Fixed price item",C15*D15,0))) -> 0
E16: =IF(B16="Labour hours",C16*IF(D16="",Rates!$B$4,D16),IF(B16="Materials at cost",C16*D16*(1+Rates!$B$5),IF(B16="Fixed price item",C16*D16,0))) -> 0
E17: =IF(B17="Labour hours",C17*IF(D17="",Rates!$B$4,D17),IF(B17="Materials at cost",C17*D17*(1+Rates!$B$5),IF(B17="Fixed price item",C17*D17,0))) -> 0
E18: =IF(B18="Labour hours",C18*IF(D18="",Rates!$B$4,D18),IF(B18="Materials at cost",C18*D18*(1+Rates!$B$5),IF(B18="Fixed price item",C18*D18,0))) -> 0
E19: =IF(B19="Labour hours",C19*IF(D19="",Rates!$B$4,D19),IF(B19="Materials at cost",C19*D19*(1+Rates!$B$5),IF(B19="Fixed price item",C19*D19,0))) -> 0
E20: =IF(B20="Labour hours",C20*IF(D20="",Rates!$B$4,D20),IF(B20="Materials at cost",C20*D20*(1+Rates!$B$5),IF(B20="Fixed price item",C20*D20,0))) -> 0
E21: =IF(B21="Labour hours",C21*IF(D21="",Rates!$B$4,D21),IF(B21="Materials at cost",C21*D21*(1+Rates!$B$5),IF(B21="Fixed price item",C21*D21,0))) -> 0
A22: Labour hours: leave the rate blank to use your standard rate. Materials at cost: margin is added automatically.
A24: Labour | B24: =SUMIF(B7:B21,"Labour hours",E7:E21) -> 540
A25: Materials (incl. margin) | B25: =SUMIF(B7:B21,"Materials at cost",E7:E21) -> 862.5
A26: Fixed price items | B26: =SUMIF(B7:B21,"Fixed price item",E7:E21) -> 250
A27: Contingency | B27: =IF(B4="Y",(B24+B25+B26)*Rates!$B$6,0) -> 0
A28: Price ex GST (min. charge applies) | B28: =ROUND(MAX(B24+B25+B26+B27,Rates!$B$9),0) -> 1653
A29: GST | B29: =ROUND(B28*Rates!$B$7,0) -> 165
A30: TOTAL inc GST | B30: =B28+B29 -> 1818
A31: Deposit on acceptance (10% max) | B31: =ROUND(B30*Rates!$B$8,0) -> 182
A32: Labour hours on site | B32: =SUMIF(B7:B21,"Labour hours",C7:C21) -> 6
A34: Checks (NSW)
A35: Written contract needed (over $5,000 inc GST)? | B35: =IF(B30>5000,"YES: small jobs contract before starting","No") -> No
A36: Large job contract + HBCF insurance (over $20,000)? | B36: =IF(B30>20000,"YES: get icare HBCF cover BEFORE taking deposit","No") -> No
